robotmk.py
robotframework_robotmk-1.0.4.dist-info/LICENSE
robotframework_robotmk-1.0.4.dist-info/METADATA
robotframework_robotmk-1.0.4.dist-info/WHEEL
robotframework_robotmk-1.0.4.dist-info/top_level.txt
robotframework_robotmk-1.0.4.dist-info/RECORD
