Metadata-Version: 2.1
Name: robotframework-robotmk
Version: 1.0.4
Summary: UNKNOWN
Home-page: https://github.com/simonmeggle/robotframework-robotmk
Author: Simon Meggle
Author-email: simon.meggle@elabit.de
License: GPLv3
Platform: UNKNOWN
License-File: LICENSE
